setup.py
neurospaces/__cbi__.py
neurospaces/__init__.py
neurospaces/launcher.py
neurospaces/packages.py
neurospaces/shell.py
neurospaces.egg-info/PKG-INFO
neurospaces.egg-info/SOURCES.txt
neurospaces.egg-info/dependency_links.txt
neurospaces.egg-info/top_level.txt